flask_securelogin/SecureAuth.py
flask_securelogin/__init__.py
flask_securelogin/account.py
flask_securelogin/errors.py
flask_securelogin/exception.py
flask_securelogin/models.py
flask_securelogin/routes.py
flask_securelogin/tokens.py
flask_securelogin/sms/OTPGenerator.py
flask_securelogin/sms/SMSBaseSender.py
flask_securelogin/sms/SMSCall.py
flask_securelogin/sms/SMSFactory.py
flask_securelogin/sms/TencentAPIClient.py
flask_securelogin/sms/TwilioClient.py
flask_securelogin/sms/UniSMSClient.py
flask_securelogin/sms/__init__.py
flask_securelogin/sms/models.py
flask_securelogin-0.1.8.dist-info/METADATA
flask_securelogin-0.1.8.dist-info/WHEEL
flask_securelogin-0.1.8.dist-info/top_level.txt
flask_securelogin-0.1.8.dist-info/RECORD
